configml/__init__.py
configml/backtest.py
configml/datasets.py
configml-0.0.1.dist-info/LICENSE
configml-0.0.1.dist-info/METADATA
configml-0.0.1.dist-info/WHEEL
configml-0.0.1.dist-info/top_level.txt
configml-0.0.1.dist-info/RECORD
