Metadata-Version: 2.1
Name: configml
Version: 0.0.1
Summary: Configured Machine Learning
Home-page: UNKNOWN
Author: ['Wenting Tu']
License: UNKNOWN
Platform: UNKNOWN
License-File: LICENSE
